[
  {
    "id": "s1",
    "billNo": "B-001",
    "customerId": "1",
    "date": "2024-05-20",
    "saleType": "credit",
    "items": [
      {
        "inventoryItemId": "i1",
        "quantity": 10,
        "salePrice": 60000
      },
      {
        "inventoryItemId": "i3",
        "quantity": 5,
        "salePrice": 65000
      }
    ],
    "amountPaid": 500000,
    "paymentMethod": "card",
    "paidTo": "Faisal Rehman"
  },
  {
    "id": "s2",
    "billNo": "B-002",
    "customerId": "2",
    "date": "2024-06-10",
    "saleType": "cash",
    "items": [
      {
        "inventoryItemId": "i4",
        "quantity": 20,
        "salePrice": 35000
      }
    ],
    "amountPaid": 700000,
    "paymentMethod": "cash",
    "paidTo": "Hafiz Abdul Rasheed"
  },
  {
    "id": "s3",
    "billNo": "B-003",
    "customerId": "1",
    "date": "2025-10-05",
    "saleType": "cash",
    "items": [
      {
        "inventoryItemId": "i2",
        "quantity": 4,
        "salePrice": 4000
      }
    ],
    "amountPaid": 0,
    "paymentMethod": "cash",
    "paidTo": "Faisal Rehman"
  },
  {
    "id": "s4",
    "billNo": "B-004",
    "customerId": "1",
    "date": "2025-10-05",
    "saleType": "cash",
    "items": [
      {
        "inventoryItemId": "i3",
        "quantity": 10,
        "salePrice": 3200
      }
    ],
    "amountPaid": 50000,
    "paymentMethod": "cash",
    "paidTo": "Faisal Rehman"
  }
]